{
  "es": {
    "0": "El huevo - Comienzo de algo nuevo",
    "1": "La mujer - Amor y romance",
    "2": "El niño - Familia y descendencia",
    "3": "El mar - Viajes y cambios",
    "4": "La cama - Descanso y tranquilidad",
    "5": "El gato - Misterio y suerte",
    "6": "El perro - Amistad y lealtad",
    "7": "El ratón - Trabajo y esfuerzo",
    "8": "La leche - Abundancia y prosperidad",
    "9": "El árbol - Crecimiento y desarrollo",
    "10": "La caña - Diversión y fiesta",
    "11": "El minero - Trabajo duro",
    "12": "El soldado - Protección y seguridad",
    "13": "La viuda - Cambios importantes",
    "14": "El borracho - Celebración y excesos",
    "15": "La niña bonita - Belleza y vanidad",
    "16": "El anillo - Compromiso y unión",
    "17": "La desgracia - Advertencia",
    "18": "La sangre - Pasión y energía",
    "19": "El pescado - Abundancia",
    "20": "La fiesta - Celebración",
    "21": "La mujer - Amor y romance",
    "22": "El loco - Cambios inesperados",
    "23": "El mar - Viajes y cambios",
    "24": "El caballo - Fuerza y libertad",
    "25": "El gato - Misterio y suerte",
    "26": "El perro - Amistad y lealtad",
    "27": "El ratón - Trabajo y esfuerzo",
    "28": "La leche - Abundancia y prosperidad",
    "29": "El árbol - Crecimiento y desarrollo",
    "30": "La caña - Diversión y fiesta",
    "31": "El minero - Trabajo duro",
    "32": "El soldado - Protección y seguridad",
    "33": "La viuda - Cambios importantes",
    "34": "El borracho - Celebración y excesos",
    "35": "La niña bonita - Belleza y vanidad",
    "36": "El anillo - Compromiso y unión",
    "37": "La desgracia - Advertencia",
    "38": "La sangre - Pasión y energía",
    "39": "El pescado - Abundancia",
    "40": "La fiesta - Celebración",
    "41": "La mujer - Amor y romance",
    "42": "El loco - Cambios inesperados",
    "43": "El mar - Viajes y cambios",
    "44": "El caballo - Fuerza y libertad",
    "45": "El gato - Misterio y suerte",
    "46": "El perro - Amistad y lealtad",
    "47": "El ratón - Trabajo y esfuerzo",
    "48": "La leche - Abundancia y prosperidad",
    "49": "El árbol - Crecimiento y desarrollo",
    "50": "La caña - Diversión y fiesta",
    "51": "El minero - Trabajo duro",
    "52": "El soldado - Protección y seguridad",
    "53": "La viuda - Cambios importantes",
    "54": "El borracho - Celebración y excesos",
    "55": "La niña bonita - Belleza y vanidad",
    "56": "El anillo - Compromiso y unión",
    "57": "La desgracia - Advertencia",
    "58": "La sangre - Pasión y energía",
    "59": "El pescado - Abundancia",
    "60": "La fiesta - Celebración",
    "61": "La mujer - Amor y romance",
    "62": "El loco - Cambios inesperados",
    "63": "El mar - Viajes y cambios",
    "64": "El caballo - Fuerza y libertad",
    "65": "El gato - Misterio y suerte",
    "66": "El perro - Amistad y lealtad",
    "67": "El ratón - Trabajo y esfuerzo",
    "68": "La leche - Abundancia y prosperidad",
    "69": "El árbol - Crecimiento y desarrollo",
    "70": "La caña - Diversión y fiesta",
    "71": "El minero - Trabajo duro",
    "72": "El soldado - Protección y seguridad",
    "73": "La viuda - Cambios importantes",
    "74": "El borracho - Celebración y excesos",
    "75": "La niña bonita - Belleza y vanidad",
    "76": "El anillo - Compromiso y unión",
    "77": "La desgracia - Advertencia",
    "78": "La sangre - Pasión y energía",
    "79": "El pescado - Abundancia",
    "80": "La fiesta - Celebración",
    "81": "La mujer - Amor y romance",
    "82": "El loco - Cambios inesperados",
    "83": "El mar - Viajes y cambios",
    "84": "El caballo - Fuerza y libertad",
    "85": "El gato - Misterio y suerte",
    "86": "El perro - Amistad y lealtad",
    "87": "El ratón - Trabajo y esfuerzo",
    "88": "La leche - Abundancia y prosperidad",
    "89": "El árbol - Crecimiento y desarrollo",
    "90": "La caña - Diversión y fiesta",
    "91": "El minero - Trabajo duro",
    "92": "El soldado - Protección y seguridad",
    "93": "La viuda - Cambios importantes",
    "94": "El borracho - Celebración y excesos",
    "95": "La niña bonita - Belleza y vanidad",
    "96": "El anillo - Compromiso y unión",
    "97": "La desgracia - Advertencia",
    "98": "La sangre - Pasión y energía",
    "99": "El pescado - Abundancia"
  },
  "en": {
    "0": "The egg - New beginnings",
    "1": "The woman - Love and romance",
    "2": "The child - Family and offspring",
    "3": "The sea - Travel and changes",
    "4": "The bed - Rest and tranquility",
    "5": "The cat - Mystery and luck",
    "6": "The dog - Friendship and loyalty",
    "7": "The mouse - Work and effort",
    "8": "The milk - Abundance and prosperity",
    "9": "The tree - Growth and development",
    "10": "The cane - Fun and party",
    "11": "The miner - Hard work",
    "12": "The soldier - Protection and security",
    "13": "The widow - Important changes",
    "14": "The drunk - Celebration and excess",
    "15": "The pretty girl - Beauty and vanity",
    "16": "The ring - Commitment and union",
    "17": "The misfortune - Warning",
    "18": "The blood - Passion and energy",
    "19": "The fish - Abundance",
    "20": "The party - Celebration",
    "21": "The woman - Love and romance",
    "22": "The fool - Unexpected changes",
    "23": "The sea - Travel and changes",
    "24": "The horse - Strength and freedom",
    "25": "The cat - Mystery and luck",
    "26": "The dog - Friendship and loyalty",
    "27": "The mouse - Work and effort",
    "28": "The milk - Abundance and prosperity",
    "29": "The tree - Growth and development",
    "30": "The cane - Fun and party",
    "31": "The miner - Hard work",
    "32": "The soldier - Protection and security",
    "33": "The widow - Important changes",
    "34": "The drunk - Celebration and excess",
    "35": "The pretty girl - Beauty and vanity",
    "36": "The ring - Commitment and union",
    "37": "The misfortune - Warning",
    "38": "The blood - Passion and energy",
    "39": "The fish - Abundance",
    "40": "The party - Celebration",
    "41": "The woman - Love and romance",
    "42": "The fool - Unexpected changes",
    "43": "The sea - Travel and changes",
    "44": "The horse - Strength and freedom",
    "45": "The cat - Mystery and luck",
    "46": "The dog - Friendship and loyalty",
    "47": "The mouse - Work and effort",
    "48": "The milk - Abundance and prosperity",
    "49": "The tree - Growth and development",
    "50": "The cane - Fun and party",
    "51": "The miner - Hard work",
    "52": "The soldier - Protection and security",
    "53": "The widow - Important changes",
    "54": "The drunk - Celebration and excess",
    "55": "The pretty girl - Beauty and vanity",
    "56": "The ring - Commitment and union",
    "57": "The misfortune - Warning",
    "58": "The blood - Passion and energy",
    "59": "The fish - Abundance",
    "60": "The party - Celebration",
    "61": "The woman - Love and romance",
    "62": "The fool - Unexpected changes",
    "63": "The sea - Travel and changes",
    "64": "The horse - Strength and freedom",
    "65": "The cat - Mystery and luck",
    "66": "The dog - Friendship and loyalty",
    "67": "The mouse - Work and effort",
    "68": "The milk - Abundance and prosperity",
    "69": "The tree - Growth and development",
    "70": "The cane - Fun and party",
    "71": "The miner - Hard work",
    "72": "The soldier - Protection and security",
    "73": "The widow - Important changes",
    "74": "The drunk - Celebration and excess",
    "75": "The pretty girl - Beauty and vanity",
    "76": "The ring - Commitment and union",
    "77": "The misfortune - Warning",
    "78": "The blood - Passion and energy",
    "79": "The fish - Abundance",
    "80": "The party - Celebration",
    "81": "The woman - Love and romance",
    "82": "The fool - Unexpected changes",
    "83": "The sea - Travel and changes",
    "84": "The horse - Strength and freedom",
    "85": "The cat - Mystery and luck",
    "86": "The dog - Friendship and loyalty",
    "87": "The mouse - Work and effort",
    "88": "The milk - Abundance and prosperity",
    "89": "The tree - Growth and development",
    "90": "The cane - Fun and party",
    "91": "The miner - Hard work",
    "92": "The soldier - Protection and security",
    "93": "The widow - Important changes",
    "94": "The drunk - Celebration and excess",
    "95": "The pretty girl - Beauty and vanity",
    "96": "The ring - Commitment and union",
    "97": "The misfortune - Warning",
    "98": "The blood - Passion and energy",
    "99": "The fish - Abundance"
  }
}
